Metadata-Version: 2.1
Name: odoo-addon-connector_ecommerce
Version: 16.0.1.0.0.13
Summary: Connector for E-Commerce
Home-page: https://github.com/OCA/connector-ecommerce
Author: Camptocamp,Akretion,Odoo Community Association (OCA)
Author-email: support@odoo-community.org
License: AGPL-3
Classifier: Programming Language :: Python
Classifier: Framework :: Odoo
Classifier: Framework :: Odoo :: 16.0
Classifier: License :: OSI Approved :: GNU Affero General Public License v3
Requires-Python: >=3.10
Requires-Dist: odoo-addon-connector<16.1dev,>=16.0dev
Requires-Dist: odoo-addon-connector-base-product<16.1dev,>=16.0dev
Requires-Dist: odoo-addon-sale-automatic-workflow-payment-mode<16.1dev,>=16.0dev
Requires-Dist: odoo-addon-sale-exception<16.1dev,>=16.0dev
Requires-Dist: odoo<16.1dev,>=16.0a
